cd_wp_api/__init__.py
cd_wp_api/version.py
cd_wp_api/wp_api.py
cd_wp_api-0.0.1.dist-info/LICENSE.md
cd_wp_api-0.0.1.dist-info/LICENSE.txt
cd_wp_api-0.0.1.dist-info/METADATA
cd_wp_api-0.0.1.dist-info/WHEEL
cd_wp_api-0.0.1.dist-info/top_level.txt
cd_wp_api-0.0.1.dist-info/RECORD
