Metadata-Version: 2.1
Name: cd_wp_api
Version: 0.0.1
Summary: A small wrapper around wordpress-api package for noobs.
Author-email: Code Docta <codedocta@gmail.com>
License: MIT
Project-URL: homepage, https://codedocta.com
Project-URL: Bug-Reports, https://github.com/codedocta/cd_wp_api/issues
Project-URL: Source, https://github.com/codedocta/cd_wp_api/
Classifier: Development Status :: 4 - Beta
Classifier: License :: OSI Approved :: MIT License
Classifier: Programming Language :: Python :: 3
Classifier: Operating System :: OS Independent
Requires-Python: >=3.6
License-File: LICENSE.md
License-File: LICENSE.txt
Requires-Dist: wordpress-api ==1.2.9
